py_appstream/__init__.py
py_appstream/component.py
py_appstream/exceptions.py
py_appstream/subcomponent.py
py_appstream/utils.py
py_appstream-0.2.2.dist-info/CC-BY-SA-4.0.txt
py_appstream-0.2.2.dist-info/CC0-1.0.txt
py_appstream-0.2.2.dist-info/LGPL-2.1-or-later.txt
py_appstream-0.2.2.dist-info/METADATA
py_appstream-0.2.2.dist-info/WHEEL
py_appstream-0.2.2.dist-info/top_level.txt
py_appstream-0.2.2.dist-info/RECORD
